pynir/Calibration.py
pynir/CalibrationTransfer.py
pynir/FeatureSelection.py
pynir/OutlierDetection.py
pynir/Preprocessing.py
pynir/Reader.py
pynir/__init__.py
pynir/utils.py
pynir/demo_data/csv_InnoSpectra/demo0.csv
pynir/demo_data/csv_InnoSpectra/demo1.csv
pynir/demo_data/csv_InnoSpectra/demo2.csv
pynir/demo_data/mat_corn/Data_Corn.mat
pynir/demo_data/mat_tablet/Data_Tablet.mat
pynir/demo_data/spa_unknown/demo0.spa
pynir/demo_data/spa_unknown/demo1.spa
pynir/demo_data/spa_unknown/demo2.spa
pynir-0.7.11.dist-info/METADATA
pynir-0.7.11.dist-info/WHEEL
pynir-0.7.11.dist-info/licenses/LICENSE.txt
pynir-0.7.11.dist-info/RECORD
