Metadata-Version: 2.4
Name: pynir
Version: 0.7.11
Summary: NIR calibration toolbox in python
Project-URL: Homepage, https://github.com/JinZhangLab/pynir
Project-URL: Bug Tracker, https://github.com/JinZhangLab/pynir/issues
Project-URL: Documentation, https://pynir.readthedocs.io/en/latest/
Author-email: J Zhang <jzhang@chemoinfolab.com>
License-File: LICENSE.txt
Classifier: License :: OSI Approved :: MIT License
Classifier: Operating System :: OS Independent
Classifier: Programming Language :: Python :: 3
Requires-Python: >=3.7
Requires-Dist: matplotlib
Requires-Dist: numpy
Requires-Dist: pywavelets
Requires-Dist: scikit-learn
Requires-Dist: scipy
